Workbook

Sheet Innovation Record
B1: Field (Question) | C1: Your Answer | D1: Sub-Answer (If applicable) | E1: Guidance | F1: ID (Hidden) | G1: Helper (Hidden) | H1: Sub Helper 1 (Hidden) | I1: Sub Helper 2 (Hidden)
A2: 1. About your innovation
A3: 1.1. Description of innovation
B4: What is the name of your innovation? | E4: Enter the name of your innovation with a maximum of 100 characters (Required) (Max 100 chars) | F4: name
B5: Provide a short description of your innovation | E5: Provide a high-level overview of your innovation. You will have the opportunity to explain its impact, target population, testing and revenue model later in the innovation record. (Required) (Max 500 chars) | F5: description
B6: Where is your head office located? | E6: If your head office is overseas but you have a UK office, use the UK address. If you are not part of a company or organisation, put where you are based. We ask this to identify the organisations and people who are in the best position to support you. (Required) | F6: officeLocation | G6: =IFERROR(VLOOKUP(C6, 'ReferenceData'!$A$1:$B$5, 2, 0), "")
B7: ⚠️ CONDITIONAL SECTION: Only answer the question below if you answered 'England' or 'Scotland' or 'Wales' or 'Northern Ireland' for 'Where is your head office located?'
B8: What is your head office postcode? | E8: (Required) (Max 8 chars) | F8: postcode
B9: ⚠️ CONDITIONAL SECTION: Only answer the question below if you answered 'I'm based outside of the UK' for 'Where is your head office located?'
B10: Which country is your head office located in? | E10: (Required) | F10: countryLocation | G10: =IFERROR(VLOOKUP(C10, 'ReferenceData'!$C$1:$D$195, 2, 0), "")
B11: Does your innovation have a website? | E11: (Required) | F11: hasWebsite | G11: =IFERROR(VLOOKUP(C11, 'ReferenceData'!$E$1:$F$2, 2, 0), "")
B12: └─ Website (⚠️ Only answer if you selected 'Yes' above) | E12: (Required) | F12: website
B13: Does your innovation have a video that explains how it works ? | F13: hasVideoDemonstration | G13: =IFERROR(VLOOKUP(C13, 'ReferenceData'!$G$1:$H$2, 2, 0), "")
B14: └─ Link (⚠️ Only answer if you selected 'Yes' above) | F14: videoDemonstrationUrl
B16: Select all the categories that can be used to describe your innovation | F16: =TEXTJOIN("; ", TRUE, G17:G29)
B17: ◽ Medical device | F17: MEDICAL_DEVICE | G17: =IF(C17="Selected", F17, "")
B18: ◽ In vitro diagnostic | F18: IN_VITRO_DIAGNOSTIC | G18: =IF(C18="Selected", F18, "")
B19: ◽ Pharmaceutical | F19: PHARMACEUTICAL | G19: =IF(C19="Selected", F19, "")
B20: ◽ Digital (including apps, platforms, software) | F20: DIGITAL | G20: =IF(C20="Selected", F20, "")
B21: ◽ Artificial intelligence (AI) | F21: AI | G21: =IF(C21="Selected", F21, "")
B22: ◽ Education or training of workforce | F22: EDUCATION | G22: =IF(C22="Selected", F22, "")
B23: ◽ Personal protective equipment (PPE) | F23: PPE | G23: =IF(C23="Selected", F23, "")
B24: ◽ Models of care and clinical pathways | F24: MODELS_CARE | G24: =IF(C24="Selected", F24, "")
B25: ◽ Estates and facilities | F25: ESTATES_FACILITIES | G25: =IF(C25="Selected", F25, "")
B26: ◽ Travel and transport | F26: TRAVEL_TRANSPORT | G26: =IF(C26="Selected", F26, "")
B27: ◽ Food and nutrition | F27: FOOD_NUTRITION | G27: =IF(C27="Selected", F27, "")
B28: ◽ Data and monitoring | F28: DATA_MONITORING | G28: =IF(C28="Selected", F28, "")
B29: ◽ Other | F29: OTHER | G29: =IF(C29="Selected", F29, "")
B31: Select a primary category to describe your innovation | E31: (Required) | F31: mainCategory | G31: =IFERROR(VLOOKUP(C31, 'ReferenceData'!$I$1:$J$13, 2, 0), "")
B32: └─ Other category (⚠️ Only answer if you selected 'Other' above) | E32: (Required) (Max 100 chars) | F32: otherCategoryDescription
B34: Is your innovation relevant to any of the following areas? | E34: We ask this to identify the organisations and people who are in the best position to support you. | F34: =TEXTJOIN("; ", TRUE, G35:G45)
B35: ◽ Data, analytics and research | F35: DATA_ANALYTICS_AND_RESEARCH | G35: =IF(C35="Selected", F35, "")
B36: ◽ Digitalising the system | F36: DIGITALISING_SYSTEM | G36: =IF(C36="Selected", F36, "")
B37: ◽ Emerging infectious diseases | F37: EMERGING_INFECTIOUS_DISEASES | G37: =IF(C37="Selected", F37, "")
B38: ◽ Hospital to community | F38: HOSPITAL_TO_COMMUNITY | G38: =IF(C38="Selected", F38, "")
B39: ◽ Improving system flow | F39: IMPROVING_SYSTEM_FLOW | G39: =IF(C39="Selected", F39, "")
B40: ◽ Net zero NHS or greener innovation | F40: NET_ZERO_GREENER_INNOVATION | G40: =IF(C40="Selected", F40, "")
B41: ◽ Patient safety and quality improvement | F41: PATIENT_SAFETY | G41: =IF(C41="Selected", F41, "")
B42: ◽ Preventive care | F42: PREVENTIVE_CARE | G42: =IF(C42="Selected", F42, "")
B43: ◽ Supporting people to manage their health | F43: SUPPORTING_PEOPLE_HEALTH | G43: =IF(C43="Selected", F43, "")
B44: ◽ Workforce resource optimisation | F44: WORKFORCE_RESOURCE_OPTIMISATION | G44: =IF(C44="Selected", F44, "")
B45: ◽ None of those listed | F45: NONE | G45: =IF(C45="Selected", F45, "")
B48: In which care settings is your innovation relevant? | F48: =TEXTJOIN("; ", TRUE, G49:G64)
B49: ◽ Academia | F49: ACADEMIA | G49: =IF(C49="Selected", F49, "")
B50: ◽ Acute trust - inpatient | F50: ACUTE_TRUSTS_INPATIENT | G50: =IF(C50="Selected", F50, "")
B51: ◽ Acute trust - outpatient | F51: ACUTE_TRUSTS_OUTPATIENT | G51: =IF(C51="Selected", F51, "")
B52: ◽ Ambulance | F52: AMBULANCE | G52: =IF(C52="Selected", F52, "")
B53: ◽ Care homes or care setting | F53: CARE_HOMES_CARE_SETTING | G53: =IF(C53="Selected", F53, "")
B54: ◽ End of life care (EOLC) | F54: END_LIFE_CARE | G54: =IF(C54="Selected", F54, "")
B55: ◽ ICS | F55: ICS | G55: =IF(C55="Selected", F55, "")
B56: ◽ Industry | F56: INDUSTRY | G56: =IF(C56="Selected", F56, "")
B57: ◽ Local authority - education | F57: LOCAL_AUTHORITY_EDUCATION | G57: =IF(C57="Selected", F57, "")
B58: ◽ Mental health | F58: MENTAL_HEALTH | G58: =IF(C58="Selected", F58, "")
B59: ◽ Pharmacies | F59: PHARMACY | G59: =IF(C59="Selected", F59, "")
B60: ◽ Primary care | F60: PRIMARY_CARE | G60: =IF(C60="Selected", F60, "")
... B64: ◽ Other | F64: OTHER | G64: =IF(C64="Selected", F64, "")
B66: What is the main purpose of your innovation? | E66: We ask this to identify the organisations and people who are in the best position to support you. (Required) | F66: mainPurpose | G66: =IFERROR(VLOOKUP(C66, 'ReferenceData'!$K$1:$L$8, 2, 0), "")
B67: What support are you seeking from the Innovation Service? | E67: For example, support with clinical trials, product development, real-world evidence, regulatory advice, or adoption. You will have the opportunity to explain how your innovation works and its benefits later in the record (Required) (Max 2000 chars) | F67: supportDescription
B68: Are you currently receiving any support for your innovation? | E68: This can include any UK funding to support the development of your innovation, or any support you are currently receiving from NHS Innovation Service organisations (opens in a new window). (Required) (Max 2000 chars) | F68: currentlyReceivingSupport
B70: Has this innovation received support from any of these programmes? | E70: Select all that apply, or select no, if not relevant. | F70: =TEXTJOIN("; ", TRUE, G71:G87)
B71: ◽ No | F71: No | G71: =IF(C71="Selected", F71, "")
B72: ◽ Artificial Intelligence in Health and Care Award | F72: Artificial Intelligence in Health and Care Award | G72: =IF(C72="Selected", F72, "")
B73: ◽ Clinical Entrepreneur Programme (CEP) | F73: Clinical Entrepreneur Programme (CEP) | G73: =IF(C73="Selected", F73, "")
B74: ◽ Early Access to Medicines Scheme | F74: Early Access to Medicines Scheme | G74: =IF(C74="Selected", F74, "")
B75: ◽ Health Innovation Network (HIN) | F75: Health Innovation Network (HIN) | G75: =IF(C75="Selected", F75, "")
B76: ◽ Innovation and Technology Payment Programme | F76: Innovation and Technology Payment Programme | G76: =IF(C76="Selected", F76, "")
B77: ◽ Innovation for Healthcare Inequalities Programme (InHIP) | F77: Innovation for Healthcare Inequalities Programme (InHIP) | G77: =IF(C77="Selected", F77, "")
B78: ◽ Innovative Devices Access Pathway (IDAP) | F78: Innovative Devices Access Pathway (IDAP) | G78: =IF(C78="Selected", F78, "")
B79: ◽ Innovative Licensing and Access Pathway (ILAP) | F79: Innovative Licensing and Access Pathway (ILAP) | G79: =IF(C79="Selected", F79, "")
B80: ◽ NHS Innovation Accelerator (NIA) | F80: NHS Innovation Accelerator (NIA) | G80: =IF(C80="Selected", F80, "")
B81: ◽ NHS Insights Prioritisation Programme | F81: NHS Insights Prioritisation Programme | G81: =IF(C81="Selected", F81, "")
B82: ◽ NHS InSites Programme | F82: NHS InSites Programme | G82: =IF(C82="Selected", F82, "")
... B87: ◽ Test beds | F87: Test beds | G87: =IF(C87="Selected", F87, "")
A89: 2. Value proposition
A90: 2.1. Detailed understanding of needs and benefits
B91: What problem is your innovation trying to solve? | E91: Include the current consequences of the problem. For example, the process of checking a patient's pulse to determine if there is atrial fibrillation using a finger and a watch is inherently inaccurate. Using this method approximately 25% of patients are not referred to secondary care who should be (false negative) and 15% of patients who are referred are referred unnecessarily (false positive). For those patients who are not picked up at this stage, their underlying disease will progress before being correctly diagnosed. (Required) (Max 1500 chars) | F91: problemsTackled
B92: Give an overview of how your innovation works | E92: If this is or might be a medical device, include the intended purpose statement (opens in a new window). For example, GPs will identify patients with suspected atrial fibrillation from their history and reported symptoms. This innovation is a portable device that patients wear over a 7-day period. The device will monitor the patient’s heart rate continuously whilst they are wearing it. GPs will need to be trained in using the device and interpreting the results. GP practices will need to store the device and consumables. (Required) (Max 1500 chars) | F92: howInnovationWork
B93: Do you have a working product, service or prototype? | E93: (Required) | F93: hasProductServiceOrPrototype | G93: =IFERROR(VLOOKUP(C93, 'ReferenceData'!$M$1:$N$2, 2, 0), "")
B95: What are the benefits or impact of your innovation? | F95: =TEXTJOIN("; ", TRUE, G96:G125)
B96: ◽ Reduces mortality | F96: Reduces mortality | G96: =IF(C96="Selected", F96, "")
B97: ◽ Reduces need for further treatment | F97: Reduces need for further treatment | G97: =IF(C97="Selected", F97, "")
B98: ◽ Reduces adverse events | F98: Reduces adverse events | G98: =IF(C98="Selected", F98, "")
B99: ◽ Enables earlier or more accurate diagnosis | F99: Enables earlier or more accurate diagnosis | G99: =IF(C99="Selected", F99, "")
B100: ◽ Reduces risks, side effects or complications | F100: Reduces risks, side effects or complications | G100: =IF(C100="Selected", F100, "")
B101: ◽ Prevents a condition occurring or exacerbating | F101: Prevents a condition occurring or exacerbating | G101: =IF(C101="Selected", F101, "")
B102: ◽ Avoids a test, procedure or unnecessary treatment | F102: Avoids a test, procedure or unnecessary treatment | G102: =IF(C102="Selected", F102, "")
B103: ◽ Enables a test, procedure or treatment to be done non-invasively | F103: Enables a test, procedure or treatment to be done non-invasively | G103: =IF(C103="Selected", F103, "")
B104: ◽ Increases self-management | F104: Increases self-management | G104: =IF(C104="Selected", F104, "")
B105: ◽ Increases quality of life | F105: Increases quality of life | G105: =IF(C105="Selected", F105, "")
B106: ◽ Enables shared care | F106: Enables shared care | G106: =IF(C106="Selected", F106, "")
B107: ◽ Alleviates pain | F107: Alleviates pain | G107: =IF(C107="Selected", F107, "")
... B125: ◽ Other benefits for the NHS and social care | F125: Other benefits for the NHS and social care | G125: =IF(C125="Selected", F125, "")
B127: Does your innovation impact a disease or condition? | E127: (Required) | F127: impactDiseaseCondition | G127: =IFERROR(VLOOKUP(C127, 'ReferenceData'!$O$1:$P$2, 2, 0), "")
B128: ⚠️ CONDITIONAL SECTION: Only answer the question below if you answered 'Yes' for 'Does your innovation impact a disease or condition?'
B130: What diseases or conditions does your innovation impact? | E130: Start typing to view conditions. You can select as many conditions as you like. | F130: =TEXTJOIN("; ", TRUE, G131:G297)
B131: ◽ Blood and immune system conditions | F131: BLOOD_AND_IMMUNE_SYSTEM_CONDITIONS | G131: =IF(C131="Selected", F131, "")
B132: ◽ Blood and immune system conditions - Allergies | F132: BLOOD_AND_IMMUNE_SYSTEM_CONDITIONS_ALLERGIES | G132: =IF(C132="Selected", F132, "")
B133: ◽ Blood and immune system conditions - Anaphylaxis | F133: BLOOD_AND_IMMUNE_SYSTEM_CONDITIONS_ANAPHYLAXIS | G133: =IF(C133="Selected", F133, "")
B134: ◽ Blood and immune system conditions - Blood conditions | F134: BLOOD_AND_IMMUNE_SYSTEM_CONDITIONS_BLOOD_CONDITIONS | G134: =IF(C134="Selected", F134, "")
B135: ◽ Blood and immune system conditions - Lymphoedema | F135: BLOOD_AND_IMMUNE_SYSTEM_CONDITIONS_LYMPHOEDEMA | G135: =IF(C135="Selected", F135, "")
...

Sheet ReferenceData
A1: England | B1: England | C1: Afghanistan | D1: Afghanistan | E1: Yes | F1: YES | G1: Yes | H1: YES | I1: Medical device | J1: MEDICAL_DEVICE | K1: Preventing a condition or symptom from happening or worsening | L1: PREVENT_CONDITION | M1: Yes | N1: YES | O1: Yes | P1: YES | Q1: Yes | R1: YES | S1: Yes, I have one | T1: YES | U1: Yes | V1: YES | W1: Yes | X1: YES | Y1: Yes | Z1: YES | AA1: Yes | AB1: YES | AC1: A one-off innovation, or the first of its kind | AD1: ONE_OFF_INNOVATION | AE1: There is a pathway, and my innovation changes it | AF1: PATHWAY_EXISTS_AND_CHANGED | AG1: Yes | AH1: YES | AI1: Yes | AJ1: YES | AK1: Yes, I know all of them | AL1: YES_ALL | AM1: Yes | AN1: YES | AO1: Yes | AP1: YES | AQ1: Yes | AR1: YES | AS1: Yes | AT1: YES | AU1: Yes | AV1: YES | AW1: Yes | AX1: YES | AY1: Yes | AZ1: YES | BA1: Yes | BB1: YES | BC1: Yes | BD1: YES | BE1: Yes | BF1: YES | BG1: Yes | BH1: YES | BI1: Yes | BJ1: YES | BK1: Yes | BL1: YES | BM1: I have one or more patents | BN1: HAS_AT_LEAST_ONE | BO1: Yes | BP1: YES | BQ1: Yes | BR1: YES | BS1: Yes | BT1: YES | BU1: Yes, I have a detailed estimate | BV1: DETAILED_ESTIMATE | BW1: Up to 10,000 per year | BX1: UP_10000 | BY1: My innovation is cheaper to purchase | BZ1: CHEAPER | CA1: Yes | CB1: YES | CC1: Yes | CD1: YES | CE1: Yes | CF1: YES
A2: Scotland | B2: Scotland | C2: Albania | D2: Albania | E2: No | F2: NO | G2: No | H2: NO | I2: In vitro diagnostic | J2: IN_VITRO_DIAGNOSTIC | K2: Predicting the occurence of a condition or symptom | L2: PREDICT_CONDITION | M2: No | N2: NO | O2: No | P2: NO | Q2: Not yet, but I have an idea | R2: NOT_YET | S2: I am working on one | T2: WORKING_ON | U2: No | V2: NO | W2: Not yet | X2: NOT_YET | Y2: No | Z2: NO | AA2: I'm currently doing market research | AB2: IN_PROGRESS | AC2: A better alternative to those that already exist | AD2: BETTER_ALTERNATIVE | AE2: There is a pathway, and my innovation fits in to it | AF2: PATHWAY_EXISTS_AND_FITS | AG2: I am in the process of involving users in the design | AH2: IN_PROGRESS | AI2: I am in the process of testing with users | AJ2: IN_PROGRESS | AK2: Yes, I know some of them | AL2: YES_SOME | AM2: I am actively working towards it | AN2: IN_PROGRESS | AO2: I am actively working towards it | AP2: IN_PROGRESS | AQ2: I am actively working towards it | AR2: IN_PROGRESS | AS2: I am actively working towards it | AT2: IN_PROGRESS | AU2: I am actively working towards it | AV2: IN_PROGRESS | AW2: I am actively working towards it | AX2: IN_PROGRESS | AY2: I am actively working towards it | AZ2: IN_PROGRESS | BA2: I am actively working towards it | BB2: IN_PROGRESS | BC2: I am actively working towards it | BD2: IN_PROGRESS | BE2: I am actively working towards it | BF2: IN_PROGRESS | BG2: I am actively working towards it | BH2: IN_PROGRESS | BI2: I am actively working towards it | BJ2: IN_PROGRESS | BK2: I am actively working towards it | BL2: IN_PROGRESS | BM2: I have applied for one or more patents | BN2: APPLIED_AT_LEAST_ONE | BO2: No | BP2: NO | BQ2: No | BR2: NO | BS2: No | BT2: NO | BU2: Yes, I have a rough idea | BV2: ROUGH_IDEA | BW2: 10,000 to half a million per year | BX2: BETWEEN_10000_500000 | BY2: My innovation costs more to purchase, but has greater benefits that will lead to overall cost savings | BZ2: COSTS_MORE_WITH_SAVINGS | CA2: No | CB2: NO | CC2: No | CD2: NO | CE2: No | CF2: NO
A3: Wales | B3: Wales | C3: Algeria | D3: Algeria | I3: Pharmaceutical | J3: PHARMACEUTICAL | K3: Diagnosing a condition | L3: DIAGNOSE_CONDITION | Q3: No | R3: NO | S3: No, I do not have one | T3: NO | AA3: Not yet | AB3: NOT_YET | AC3: An equivalent alternative to those that already exist | AD3: EQUIVALENT_ALTERNATIVE | AE3: There is no current care pathway | AF3: NO_PATHWAY | AG3: Not yet | AH3: NOT_YET | AI3: Not yet | AJ3: NOT_YET | AK3: No | AL3: NO | AM3: Not yet | AN3: NOT_YET | AO3: Not yet | AP3: NOT_YET | AQ3: Not yet | AR3: NOT_YET | AS3: Not yet | AT3: NOT_YET | AU3: Not yet | AV3: NOT_YET | AW3: Not yet | AX3: NOT_YET | AY3: Not yet | AZ3: NOT_YET | BA3: Not yet | BB3: NOT_YET | BC3: Not yet | BD3: NOT_YET | BE3: Not yet | BF3: NOT_YET | BG3: Not yet | BH3: NOT_YET | BI3: Not yet | BJ3: NOT_YET | BK3: Not yet | BL3: NOT_YET | BM3: I do not have any patents, but believe I have freedom to operate | BN3: HAS_NONE | BQ3: I do not know | BR3: DONT_KNOW | BS3: Not relevant | BT3: NOT_RELEVANT | BU3: No | BV3: NO | BW3: More than half a million per year | BX3: MORE_THAN_500000 | BY3: My innovation costs more to purchase and has greater benefits, but will lead to higher costs overall | BZ3: COSTS_MORE | CE3: I am not sure | CF3: NOT_SURE
A4: Northern Ireland | B4: Northern Ireland | C4: Andorra | D4: Andorra | I4: Digital (including apps, platforms, software) | J4: DIGITAL | K4: Monitoring a condition, treatment or therapy | L4: MONITOR_CONDITION | AC4: A more cost-effect alternative to those that already exist | AD4: COST_EFFECT_ALTERNATIVE | AE4: I do not know | AF4: DONT_KNOW | AK4: Not relevant | AL4: NOT_RELEVANT | BW4: I am not sure | BX4: NOT_SURE | BY4: I am not sure | BZ4: NOT_SURE
A5: I'm based outside of the UK | B5: Based outside UK | C5: Angola | D5: Angola | I5: Artificial intelligence (AI) | J5: AI | K5: Providing treatment or therapy | L5: PROVIDE_TREATMENT | AC5: I am not sure | AD5: NOT_SURE | AE5: Does not form part of a care pathway | AF5: NOT_PART_PATHWAY | BW5: Not relevant to my innovation | BX5: NOT_RELEVANT
C6: Antigua and Barbuda | D6: Antigua and Barbuda | I6: Education or training of workforce | J6: EDUCATION | K6: Managing a condition | L6: MANAGE_CONDITION
C7: Argentina | D7: Argentina | I7: Personal protective equipment (PPE) | J7: PPE | K7: Enabling care, services or communication | L7: ENABLING_CARE
C8: Armenia | D8: Armenia | I8: Models of care and clinical pathways | J8: MODELS_CARE | K8: Supporting the NHS to mitigate the risks or effects of climate change and severe weather conditions | L8: RISKS_CLIMATE_CHANGE
C9: Australia | D9: Australia | I9: Estates and facilities | J9: ESTATES_FACILITIES
C10: Austria | D10: Austria | I10: Travel and transport | J10: TRAVEL_TRANSPORT
C11: Azerbaijan | D11: Azerbaijan | I11: Food and nutrition | J11: FOOD_NUTRITION
C12: Bahamas | D12: Bahamas | I12: Data and monitoring | J12: DATA_MONITORING
C13: Bahrain | D13: Bahrain | I13: Other | J13: OTHER
C14: Bangladesh | D14: Bangladesh
C15: Barbados | D15: Barbados
C16: Belarus | D16: Belarus
C17: Belgium | D17: Belgium
C18: Belize | D18: Belize
C19: Benin | D19: Benin
C20: Bhutan | D20: Bhutan
C21: Bolivia | D21: Bolivia
C22: Bosnia and Herzegovina | D22: Bosnia and Herzegovina
C23: Botswana | D23: Botswana
C24: Brazil | D24: Brazil
C25: Brunei | D25: Brunei
... C195: Zimbabwe | D195: Zimbabwe
